__init__.py
luhn.py
luhn_credit_card_validator-0.0.2.dist-info/LICENSE
luhn_credit_card_validator-0.0.2.dist-info/METADATA
luhn_credit_card_validator-0.0.2.dist-info/WHEEL
luhn_credit_card_validator-0.0.2.dist-info/top_level.txt
luhn_credit_card_validator-0.0.2.dist-info/RECORD
